ethics/__init__.py
ethics/explanations.py
ethics/language.py
ethics/solver.py
ethics/tools.py
ethics/verbalizer.py
ethics/cam/principles.py
ethics/cam/semantics.py
ethics/plans/concepts.py
ethics/plans/planner.py
ethics/plans/principles.py
ethics/plans/semantics.py
ethics-0.22.3.dist-info/DESCRIPTION.rst
ethics-0.22.3.dist-info/METADATA
ethics-0.22.3.dist-info/RECORD
ethics-0.22.3.dist-info/WHEEL
ethics-0.22.3.dist-info/metadata.json
ethics-0.22.3.dist-info/top_level.txt
