Metadata-Version: 2.0
Name: ethics
Version: 0.22.3
Summary: A python toolbox for ethical reasoning.
Home-page: http://www.hera-project.com
Author: Felix Lindner
Author-email: info@hera-project.com
License: UNKNOWN
Platform: UNKNOWN
Requires-Dist: PyYAML
Requires-Dist: pyeda
